boot.py
cidc_api/__init__.py
cidc_api/telemetry.py
cidc_api/config/__init__.py
cidc_api/config/db.py
cidc_api/config/logging.py
cidc_api/config/secrets.py
cidc_api/config/settings.py
cidc_api/models/__init__.py
cidc_api/models/code_systems.py
cidc_api/models/dataset.py
cidc_api/models/errors.py
cidc_api/models/migrations.py
cidc_api/models/models.py
cidc_api/models/schemas.py
cidc_api/models/types.py
cidc_api/models/db/stage1/__init__.py
cidc_api/models/db/stage1/additional_treatment_orm.py
cidc_api/models/db/stage1/adverse_event_orm.py
cidc_api/models/db/stage1/base_orm.py
cidc_api/models/db/stage1/baseline_clinical_assessment_orm.py
cidc_api/models/db/stage1/comorbidity_orm.py
cidc_api/models/db/stage1/consent_group_orm.py
cidc_api/models/db/stage1/demographic_orm.py
cidc_api/models/db/stage1/disease_orm.py
cidc_api/models/db/stage1/exposure_orm.py
cidc_api/models/db/stage1/gvhd_diagnosis_acute_orm.py
cidc_api/models/db/stage1/gvhd_diagnosis_chronic_orm.py
cidc_api/models/db/stage1/gvhd_organ_acute_orm.py
cidc_api/models/db/stage1/gvhd_organ_chronic_orm.py
cidc_api/models/db/stage1/medical_history_orm.py
cidc_api/models/db/stage1/other_malignancy_orm.py
cidc_api/models/db/stage1/participant_orm.py
cidc_api/models/db/stage1/prior_treatment_orm.py
cidc_api/models/db/stage1/radiotherapy_dose_orm.py
cidc_api/models/db/stage1/response_by_system_orm.py
cidc_api/models/db/stage1/response_orm.py
cidc_api/models/db/stage1/specimen_orm.py
cidc_api/models/db/stage1/stem_cell_transplant_orm.py
cidc_api/models/db/stage1/surgery_orm.py
cidc_api/models/db/stage1/therapy_agent_dose_orm.py
cidc_api/models/db/stage1/treatment_orm.py
cidc_api/models/db/stage1/trial_orm.py
cidc_api/models/db/stage2/__init__.py
cidc_api/models/db/stage2/additional_treatment_orm.py
cidc_api/models/db/stage2/administrative_person_orm.py
cidc_api/models/db/stage2/administrative_role_assignment_orm.py
cidc_api/models/db/stage2/adverse_event_orm.py
cidc_api/models/db/stage2/arm_orm.py
nci_cidc_api_modules-1.2.55.dist-info/licenses/LICENSE
nci_cidc_api_modules-1.2.55.dist-info/METADATA
nci_cidc_api_modules-1.2.55.dist-info/WHEEL
nci_cidc_api_modules-1.2.55.dist-info/top_level.txt
nci_cidc_api_modules-1.2.55.dist-info/RECORD
