Metadata-Version: 2.4
Name: nci_cidc_api_modules
Version: 1.2.55
Summary: SQLAlchemy data models and configuration tools used in the NCI CIDC API
Home-page: https://github.com/NCI-CIDC/cidc-api-gae
License: MIT license
Requires-Python: >=3.13
License-File: LICENSE
Requires-Dist: cachetools>=6.2.4
Requires-Dist: certifi>=2026.1.4
Requires-Dist: cloud-sql-python-connector[pg8000]>=1.20.0
Requires-Dist: flask>=3.1.2
Requires-Dist: flask-migrate>=4.1.0
Requires-Dist: flask-sqlalchemy>=3.1.1
Requires-Dist: flask-talisman>=0.7.0
Requires-Dist: gcloud-aio-storage~=9.6.1
Requires-Dist: google-api-python-client>=2.188.0
Requires-Dist: google-auth==2.47.0
Requires-Dist: google-cloud-bigquery>=3.40.0
Requires-Dist: google-cloud-pubsub>=2.34.0
Requires-Dist: google-cloud-secret-manager>=2.26.0
Requires-Dist: google-cloud-storage>=3.8.0
Requires-Dist: jinja2>=3.1.6
Requires-Dist: joserfc>=1.6.1
Requires-Dist: marshmallow>=4.2.0
Requires-Dist: marshmallow-sqlalchemy>=1.4.2
Requires-Dist: numpy>=2.4.1
Requires-Dist: packaging>=25.0
Requires-Dist: pandas>=2.3.3
Requires-Dist: pyarrow>=22.0.0
Requires-Dist: pydantic~=2.12.5
Requires-Dist: python-dotenv>=1.2.1
Requires-Dist: requests>=2.32.5
Requires-Dist: sqlalchemy>=2.0.45
Requires-Dist: sqlalchemy-mixins~=2.0.5
Requires-Dist: werkzeug>=3.1.5
Requires-Dist: opentelemetry-api>=1.39.1
Requires-Dist: opentelemetry-exporter-otlp-proto-grpc>=1.39.1
Requires-Dist: opentelemetry-sdk>=1.39.1
Requires-Dist: opentelemetry-instrumentation-flask>=0.59b0
Requires-Dist: opentelemetry-instrumentation-requests>=0.59b0
Requires-Dist: opentelemetry-instrumentation-sqlalchemy>=0.59b0
Requires-Dist: opentelemetry-exporter-gcp-trace>=1.11.0
Requires-Dist: opentelemetry-propagator-gcp>=1.11.0
Requires-Dist: nci-cidc-schemas==0.28.12
Dynamic: description
Dynamic: description-content-type
Dynamic: home-page
Dynamic: license
Dynamic: license-file
Dynamic: requires-dist
Dynamic: requires-python
Dynamic: summary
